magodo/__init__.py
magodo/_common.py
magodo/_magic.py
magodo/_todo.py
magodo/dates.py
magodo/py.typed
magodo/tags.py
magodo/types.py
magodo-1.1.1.dist-info/METADATA
magodo-1.1.1.dist-info/WHEEL
magodo-1.1.1.dist-info/top_level.txt
magodo-1.1.1.dist-info/RECORD
